cf_upgrade.py
cf_upgrade-1.0.2.dist-info/DESCRIPTION.rst
cf_upgrade-1.0.2.dist-info/METADATA
cf_upgrade-1.0.2.dist-info/RECORD
cf_upgrade-1.0.2.dist-info/WHEEL
cf_upgrade-1.0.2.dist-info/entry_points.txt
cf_upgrade-1.0.2.dist-info/metadata.json
cf_upgrade-1.0.2.dist-info/top_level.txt
