Metadata-Version: 2.0
Name: cf-upgrade
Version: 1.0.2
Summary: Trivial AWS CloudFormation updater
Home-page: https://github.com/curvetips/cf_upgrade
Author: Wichert Akkerman
Author-email: wichert@wiggy.net
License: BSD
Keywords: aws cloudformation
Platform: UNKNOWN
Classifier: Intended Audience :: Developers
Classifier: License :: DFSG approved
Classifier: License :: OSI Approved :: BSD License
Classifier: Operating System :: OS Independent
Classifier: Programming Language :: Python :: 2
Classifier: Programming Language :: Python :: 3
Requires-Dist: boto3
Requires-Dist: click
Requires-Dist: tabulate
